app/05/pocoisa/rfile.v
`include "def.h"
module rfile (
 input clk,
 input [`REG_W-1:0] aadr, badr, cadr,
 output [`DATA_W-1:0] a, b,
 input [`DATA_W-1:0] c, 
 input we);

	reg [`DATA_W-1:0] r0, r1, r2, r3, r4, r5, r6, r7;

	assign a = aadr == 0 ? r0:
		aadr == 1 ? r1:
		aadr == 2 ? r2:
		aadr == 3 ? r3:
		aadr == 4 ? r4:
		aadr == 5 ? r5:
		aadr == 6 ? r6: r7;
	assign b = badr == 0 ? r0:
		badr == 1 ? r1:
		badr == 2 ? r2:
		badr == 3 ? r3:
		badr == 4 ? r4:
		badr == 5 ? r5:
		badr == 6 ? r6: r7;

	always @(posedge clk) begin
		if(we) 
		case(cadr) 
			0: r0 <= c;
			1: r1 <= c;
			2: r2 <= c;
			3: r3 <= c;
			4: r4 <= c;
			5: r5 <= c;
			6: r6 <= c;
			default: r7 <= c;
		endcase
	end

endmodule

app/05/pocoisa/alu.v
`include "def.h"

module alu (
  input [`DATA_W-1:0] a, b, 
  input [`SEL_W-1:0] s,
  output [`DATA_W-1:0] y );
  assign y = s==`ALU_THA ? a:
             s==`ALU_THB ? b:
             s==`ALU_AND ? a & b:
             s==`ALU_OR ? a | b:
             s==`ALU_SL ? a << 1:
             s==`ALU_SR ? a >> 1:
             s==`ALU_ADD ? a + b: a - b ;
endmodule

app/05/pocoisa/poco.v
`include "def.h"
module poco(
input clk, rst_n,
input [`DATA_W-1:0] idatain,
input [`DATA_W-1:0] ddatain,
output [`DATA_W-1:0] iaddr, daddr,
output [`DATA_W-1:0] ddataout,
output we);

reg [`DATA_W-1:0] pc;
wire [`DATA_W-1:0] rf_a, rf_b, rf_c;
wire [`DATA_W-1:0] alu_b, alu_y;
wire [`OPCODE_W-1:0] opcode;
wire [`OPCODE_W-1:0] func;
wire [`REG_W-1:0] rs, rd;
wire [`SEL_W-1:0] com;
wire [`IMM_W-1:0] imm;
wire rwe;
wire st_op, addi_op, ld_op, alu_op;
wire ldi_op, ldiu_op, addiu_op, ori_op;
wire ldhi_op;

assign ddataout = rf_a;
assign iaddr = pc;
assign daddr = rf_b;

assign {opcode, rd, rs, func} = idatain;
assign imm = idatain[`IMM_W-1:0];

// Decorder
assign st_op = (opcode == `OP_REG) & (func == `F_ST);
assign ld_op = (opcode == `OP_REG) & (func == `F_LD);
assign alu_op = (opcode == `OP_REG) & (func[4:3] == 2'b00); 
assign ldi_op = (opcode == `OP_LDI);
assign ldiu_op = (opcode == `OP_LDIU);
assign addi_op = (opcode == `OP_ADDI);
assign addiu_op = (opcode == `OP_ADDIU);
assign ldhi_op = (opcode == `OP_LDHI);

assign we = st_op;

assign alu_b = (addi_op | ldi_op) ? {{8{imm[7]}},imm} :
		(addiu_op | ldiu_op) ? {8'b0,imm} : rf_b;

assign com = (addi_op | addiu_op ) ? `ALU_ADD: 
		(ldi_op | ldiu_op ) ? `ALU_THB: func[`SEL_W-1:0];

assign rf_c = ld_op  ? ddatain : alu_y;
assign rwe = ld_op  | alu_op | ldi_op | ldiu_op | addi_op | addiu_op ;

alu alu_1(.a(rf_a), .b(alu_b), .s(com), .y(alu_y));

rfile rfile_1(.clk(clk), .a(rf_a), .aadr(rd), .b(rf_b), .badr(rs), 
	.c(rf_c), .cadr(rd), .we(rwe));

always @(posedge clk or negedge rst_n) 
begin 
   if(!rst_n) pc <= 0;
   else 
     pc <= pc+1;
end

endmodule

app/05/pocoisa/test_poco.v
/* test bench */
`timescale 1ns/1ps
`include "def.h"
module test;
parameter STEP = 10;
   reg clk, rst_n;
   wire [`DATA_W-1:0] ddataout ;
   wire [`DATA_W-1:0] daddr, iaddr;
   wire we;
   reg [`DATA_W-1:0] dmem [0:`DEPTH-1];
   reg [`DATA_W-1:0] imem [0:`DEPTH-1];

   always #(STEP/2) begin
            clk <= ~clk;
   end

   poco poco_1(.clk(clk), .rst_n(rst_n), .idatain(imem[iaddr]),
               .ddatain(dmem[daddr]), .iaddr(iaddr), .daddr(daddr),
               .ddataout(ddataout), .we(we));

   always @(posedge clk) 
   begin 
      if(we) dmem[daddr] <= ddataout;
   end

   initial begin
      $dumpfile("poco.vcd");
      $dumpvars(0,test);
      $readmemh("dmem.dat", dmem);
      $readmemb("imem.dat", imem);
      clk <= `DISABLE;
      rst_n <= `ENABLE_N;
   #(STEP*1/4)
   #STEP
      rst_n <= `DISABLE_N;
   #(STEP*100)            
   $finish;
   end

   always @(negedge clk) begin
      $display("pc:%h idatain:%b ", poco_1.pc, poco_1.idatain);
      $display("reg:%h %h %h %h %h %h %h %h", 
	poco_1.rfile_1.r0, poco_1.rfile_1.r1, poco_1.rfile_1.r2,
	poco_1.rfile_1.r3, poco_1.rfile_1.r4, poco_1.rfile_1.r5,
	poco_1.rfile_1.r6, poco_1.rfile_1.r7);
      $display("dmem:%h %h %h %h", dmem[0], dmem[1], dmem[2], dmem[3]);
   end
endmodule

app/05/pocoisa/poco.vcd
$date
	Tue Oct 25 02:54:08 2022
$end
$version
	Icarus Verilog
$end
$timescale
	1ps
$end
$scope module test $end
$var wire 1 ! we $end
$var wire 16 " iaddr [15:0] $end
$var wire 16 # ddataout [15:0] $end
$var wire 16 $ daddr [15:0] $end
$var reg 1 % clk $end
$var reg 1 & rst_n $end
$scope module poco_1 $end
$var wire 1 ' alu_op $end
$var wire 1 % clk $end
$var wire 16 ( daddr [15:0] $end
$var wire 16 ) ddatain [15:0] $end
$var wire 16 * ddataout [15:0] $end
$var wire 16 + idatain [15:0] $end
$var wire 1 , ld_op $end
$var wire 1 & rst_n $end
$var wire 1 - rwe $end
$var wire 1 . st_op $end
$var wire 1 ! we $end
$var wire 3 / rs [2:0] $end
$var wire 16 0 rf_c [15:0] $end
$var wire 16 1 rf_b [15:0] $end
$var wire 16 2 rf_a [15:0] $end
$var wire 3 3 rd [2:0] $end
$var wire 5 4 opcode [4:0] $end
$var wire 1 5 ldiu_op $end
$var wire 1 6 ldi_op $end
$var wire 1 7 ldhi_op $end
$var wire 8 8 imm [7:0] $end
$var wire 16 9 iaddr [15:0] $end
$var wire 5 : func [4:0] $end
$var wire 3 ; com [2:0] $end
$var wire 16 < alu_y [15:0] $end
$var wire 16 = alu_b [15:0] $end
$var wire 1 > addiu_op $end
$var wire 1 ? addi_op $end
$var reg 16 @ pc [15:0] $end
$scope module alu_1 $end
$var wire 16 A b [15:0] $end
$var wire 3 B s [2:0] $end
$var wire 16 C y [15:0] $end
$var wire 16 D a [15:0] $end
$upscope $end
$scope module rfile_1 $end
$var wire 3 E aadr [2:0] $end
$var wire 3 F badr [2:0] $end
$var wire 16 G c [15:0] $end
$var wire 3 H cadr [2:0] $end
$var wire 1 % clk $end
$var wire 1 - we $end
$var wire 16 I b [15:0] $end
$var wire 16 J a [15:0] $end
$var reg 16 K r0 [15:0] $end
$var reg 16 L r1 [15:0] $end
$var reg 16 M r2 [15:0] $end
$var reg 16 N r3 [15:0] $end
$var reg 16 O r4 [15:0] $end
$var reg 16 P r5 [15:0] $end
$var reg 16 Q r6 [15:0] $end
$var reg 16 R r7 [15:0] $end
$upscope $end
$upscope $end
$upscope $end
$enddefinitions $end
#0
$dumpvars
bx R
bx Q
bx P
bx O
bx N
bx M
bx L
bx K
bx J
bx I
b0 H
b0 G
b0 F
b0 E
bx D
b0 C
b1 B
b0 A
b0 @
0?
0>
b0 =
b0 <
b1 ;
b0 :
b0 9
b0 8
07
16
05
b1000 4
b0 3
bx 2
bx 1
b0 0
b0 /
0.
1-
0,
b100000000000000 +
bx *
bx )
bx (
0'
0&
0%
bx $
bx #
b0 "
0!
$end
#5000
b0 #
b0 *
b0 2
b0 D
b0 J
b1000 )
b0 $
b0 (
b0 1
b0 I
b0 K
1%
#10000
0%
#12000
1&
#15000
1-
b0 <
b0 C
b1000 0
b1000 G
bx #
bx *
bx 2
bx D
bx J
1,
b0 =
b0 A
06
b0 4
b1 3
b1 E
b1 H
b1001 :
b1001 8
b100001001 +
b1 "
b1 9
b1 @
1%
#20000
0%
#25000
b1 <
b1 C
b1 =
b1 A
b1 0
b1 G
b0 #
b0 *
b0 2
b0 D
b0 J
0,
16
b1000 4
b0 3
b0 E
b0 H
b1 :
b1 8
b1000 L
b100000000000001 +
b10 "
b10 9
b10 @
1%
#30000
0%
#35000
1-
b1 <
b1 C
b101 0
b101 G
1,
b1 =
b1 A
bx #
bx *
bx 2
bx D
bx J
b101 )
b1 $
b1 (
b1 1
b1 I
06
b0 4
b10 3
b10 E
b10 H
b1001 :
b1001 8
b1 K
b1000001001 +
b11 "
b11 9
b11 @
1%
#40000
0%
#45000
b1101 <
b1101 C
b101 =
b101 A
b110 ;
b110 B
b1000 #
b1000 *
b1000 2
b1000 D
b1000 J
b1101 0
b1101 G
1'
bx )
b101 $
b101 (
b101 1
b101 I
0,
b1 3
b1 E
b1 H
b10 /
b10 F
b110 :
b1000110 8
b101 M
b101000110 +
b100 "
b100 9
b100 @
1%
#50000
0%
#55000
b10 0
b10 G
b10 <
b10 C
b1 ;
b1 B
b10 =
b10 A
0'
b1 #
b1 *
b1 2
b1 D
b1 J
b101 )
b1 $
b1 (
b1 1
b1 I
16
b1000 4
b0 3
b0 E
b0 H
b0 /
b0 F
b10 :
b10 8
b1101 L
b100000000000010 +
b101 "
b101 9
b101 @
1%
#60000
0%
#65000
0-
b1101 0
b1101 G
b0 ;
b0 B
b1101 <
b1101 C
1!
1.
b10 =
b10 A
b1101 #
b1101 *
b1101 2
b1101 D
b1101 J
bx )
b10 $
b10 (
b10 1
b10 I
06
b0 4
b1 3
b1 E
b1 H
b1000 :
b1000 8
b10 K
b100001000 +
b110 "
b110 9
b110 @
1%
#70000
0%
#75000
1-
b1 ;
b1 B
b0 0
b0 G
b0 =
b0 A
b0 <
b0 C
b10 #
b10 *
b10 2
b10 D
b10 J
0!
0.
16
b1000 4
b0 3
b0 E
b0 H
b0 :
b0 8
b1101 )
b100000000000000 +
b111 "
b111 9
b111 @
1%
#80000
0%
#85000
1-
b0 <
b0 C
b1000 0
b1000 G
1,
b0 =
b0 A
bx #
bx *
bx 2
bx D
bx J
b1000 )
b0 $
b0 (
b0 1
b0 I
06
b0 4
b11 3
b11 E
b11 H
b1001 :
b1001 8
b0 K
b1100001001 +
b1000 "
b1000 9
b1000 @
1%
#90000
0%
#95000
b1 <
b1 C
b1 =
b1 A
b1 0
b1 G
b0 #
b0 *
b0 2
b0 D
b0 J
0,
16
b1000 4
b0 3
b0 E
b0 H
b1 :
b1 8
b1000 N
b100000000000001 +
b1001 "
b1001 9
b1001 @
1%
#100000
0%
#105000
1-
b1 <
b1 C
b101 0
b101 G
1,
b1 =
b1 A
bx #
bx *
bx 2
bx D
bx J
b101 )
b1 $
b1 (
b1 1
b1 I
06
b0 4
b100 3
b100 E
b100 H
b1001 :
b1001 8
b1 K
b10000001001 +
b1010 "
b1010 9
b1010 @
1%
#110000
0%
#115000
b11 <
b11 C
b1000 #
b1000 *
b1000 2
b1000 D
b1000 J
b101 =
b101 A
b111 ;
b111 B
b11 0
b11 G
1'
bx )
b101 $
b101 (
b101 1
b101 I
0,
b11 3
b11 E
b11 H
b100 /
b100 F
b111 :
b10000111 8
b101 O
b1110000111 +
b1011 "
b1011 9
b1011 @
1%
#120000
0%
#125000
b1111 0
b1111 G
b1111 <
b1111 C
b11 =
b11 A
b11 $
b11 (
b11 1
b11 I
b11 ;
b11 B
b1101 #
b1101 *
b1101 2
b1101 D
b1101 J
b1 3
b1 E
b1 H
b11 /
b11 F
b11 :
b1100011 8
b11 N
b101100011 +
b1100 "
b1100 9
b1100 @
1%
#130000
0%
#135000
b10 0
b10 G
b10 <
b10 C
b1 ;
b1 B
b10 =
b10 A
0'
b1 #
b1 *
b1 2
b1 D
b1 J
b101 )
b1 $
b1 (
b1 1
b1 I
16
b1000 4
b0 3
b0 E
b0 H
b0 /
b0 F
b10 :
b10 8
b1111 L
b100000000000010 +
b1101 "
b1101 9
b1101 @
1%
#140000
0%
#145000
0-
b1111 0
b1111 G
b0 ;
b0 B
b1111 <
b1111 C
1!
1.
b10 =
b10 A
b1111 #
b1111 *
b1111 2
b1111 D
b1111 J
b1101 )
b10 $
b10 (
b10 1
b10 I
06
b0 4
b1 3
b1 E
b1 H
b1000 :
b1000 8
b10 K
b100001000 +
b1110 "
b1110 9
b1110 @
1%
#150000
0%
#155000
bx =
bx A
bx ;
bx B
bx <
bx C
bx 0
bx G
x'
x-
bx #
bx *
bx 2
bx D
bx J
bx $
bx (
bx 1
bx I
x!
x.
x,
x6
x5
x?
x>
x7
bx 4
bx 3
bx E
bx H
bx /
bx F
bx :
bx 8
bx )
bx +
b1111 "
b1111 9
b1111 @
1%
#160000
0%
#165000
b10000 "
b10000 9
b10000 @
1%
#170000
0%
#175000
b10001 "
b10001 9
b10001 @
1%
#180000
0%
#185000
b10010 "
b10010 9
b10010 @
1%
#190000
0%
#195000
b10011 "
b10011 9
b10011 @
1%
#200000
0%
#205000
b10100 "
b10100 9
b10100 @
1%
#210000
0%
#215000
b10101 "
b10101 9
b10101 @
1%
#220000
0%
#225000
b10110 "
b10110 9
b10110 @
1%
#230000
0%
#235000
b10111 "
b10111 9
b10111 @
1%
#240000
0%
#245000
b11000 "
b11000 9
b11000 @
1%
#250000
0%
#255000
b11001 "
b11001 9
b11001 @
1%
#260000
0%
#265000
b11010 "
b11010 9
b11010 @
1%
#270000
0%
#275000
b11011 "
b11011 9
b11011 @
1%
#280000
0%
#285000
b11100 "
b11100 9
b11100 @
1%
#290000
0%
#295000
b11101 "
b11101 9
b11101 @
1%
#300000
0%
#305000
b11110 "
b11110 9
b11110 @
1%
#310000
0%
#315000
b11111 "
b11111 9
b11111 @
1%
#320000
0%
#325000
b100000 "
b100000 9
b100000 @
1%
#330000
0%
#335000
b100001 "
b100001 9
b100001 @
1%
#340000
0%
#345000
b100010 "
b100010 9
b100010 @
1%
#350000
0%
#355000
b100011 "
b100011 9
b100011 @
1%
#360000
0%
#365000
b100100 "
b100100 9
b100100 @
1%
#370000
0%
#375000
b100101 "
b100101 9
b100101 @
1%
#380000
0%
#385000
b100110 "
b100110 9
b100110 @
1%
#390000
0%
#395000
b100111 "
b100111 9
b100111 @
1%
#400000
0%
#405000
b101000 "
b101000 9
b101000 @
1%
#410000
0%
#415000
b101001 "
b101001 9
b101001 @
1%
#420000
0%
#425000
b101010 "
b101010 9
b101010 @
1%
#430000
0%
#435000
b101011 "
b101011 9
b101011 @
1%
#440000
0%
#445000
b101100 "
b101100 9
b101100 @
1%
#450000
0%
#455000
b101101 "
b101101 9
b101101 @
1%
#460000
0%
#465000
b101110 "
b101110 9
b101110 @
1%
#470000
0%
#475000
b101111 "
b101111 9
b101111 @
1%
#480000
0%
#485000
b110000 "
b110000 9
b110000 @
1%
#490000
0%
#495000
b110001 "
b110001 9
b110001 @
1%
#500000
0%
#505000
b110010 "
b110010 9
b110010 @
1%
#510000
0%
#515000
b110011 "
b110011 9
b110011 @
1%
#520000
0%
#525000
b110100 "
b110100 9
b110100 @
1%
#530000
0%
#535000
b110101 "
b110101 9
b110101 @
1%
#540000
0%
#545000
b110110 "
b110110 9
b110110 @
1%
#550000
0%
#555000
b110111 "
b110111 9
b110111 @
1%
#560000
0%
#565000
b111000 "
b111000 9
b111000 @
1%
#570000
0%
#575000
b111001 "
b111001 9
b111001 @
1%
#580000
0%
#585000
b111010 "
b111010 9
b111010 @
1%
#590000
0%
#595000
b111011 "
b111011 9
b111011 @
1%
#600000
0%
#605000
b111100 "
b111100 9
b111100 @
1%
#610000
0%
#615000
b111101 "
b111101 9
b111101 @
1%
#620000
0%
#625000
b111110 "
b111110 9
b111110 @
1%
#630000
0%
#635000
b111111 "
b111111 9
b111111 @
1%
#640000
0%
#645000
b1000000 "
b1000000 9
b1000000 @
1%
#650000
0%
#655000
b1000001 "
b1000001 9
b1000001 @
1%
#660000
0%
#665000
b1000010 "
b1000010 9
b1000010 @
1%
#670000
0%
#675000
b1000011 "
b1000011 9
b1000011 @
1%
#680000
0%
#685000
b1000100 "
b1000100 9
b1000100 @
1%
#690000
0%
#695000
b1000101 "
b1000101 9
b1000101 @
1%
#700000
0%
#705000
b1000110 "
b1000110 9
b1000110 @
1%
#710000
0%
#715000
b1000111 "
b1000111 9
b1000111 @
1%
#720000
0%
#725000
b1001000 "
b1001000 9
b1001000 @
1%
#730000
0%
#735000
b1001001 "
b1001001 9
b1001001 @
1%
#740000
0%
#745000
b1001010 "
b1001010 9
b1001010 @
1%
#750000
0%
#755000
b1001011 "
b1001011 9
b1001011 @
1%
#760000
0%
#765000
b1001100 "
b1001100 9
b1001100 @
1%
#770000
0%
#775000
b1001101 "
b1001101 9
b1001101 @
1%
#780000
0%
#785000
b1001110 "
b1001110 9
b1001110 @
1%
#790000
0%
#795000
b1001111 "
b1001111 9
b1001111 @
1%
#800000
0%
#805000
b1010000 "
b1010000 9
b1010000 @
1%
#810000
0%
#815000
b1010001 "
b1010001 9
b1010001 @
1%
#820000
0%
#825000
b1010010 "
b1010010 9
b1010010 @
1%
#830000
0%
#835000
b1010011 "
b1010011 9
b1010011 @
1%
#840000
0%
#845000
b1010100 "
b1010100 9
b1010100 @
1%
#850000
0%
#855000
b1010101 "
b1010101 9
b1010101 @
1%
#860000
0%
#865000
b1010110 "
b1010110 9
b1010110 @
1%
#870000
0%
#875000
b1010111 "
b1010111 9
b1010111 @
1%
#880000
0%
#885000
b1011000 "
b1011000 9
b1011000 @
1%
#890000
0%
#895000
b1011001 "
b1011001 9
b1011001 @
1%
#900000
0%
#905000
b1011010 "
b1011010 9
b1011010 @
1%
#910000
0%
#915000
b1011011 "
b1011011 9
b1011011 @
1%
#920000
0%
#925000
b1011100 "
b1011100 9
b1011100 @
1%
#930000
0%
#935000
b1011101 "
b1011101 9
b1011101 @
1%
#940000
0%
#945000
b1011110 "
b1011110 9
b1011110 @
1%
#950000
0%
#955000
b1011111 "
b1011111 9
b1011111 @
1%
#960000
0%
#965000
b1100000 "
b1100000 9
b1100000 @
1%
#970000
0%
#975000
b1100001 "
b1100001 9
b1100001 @
1%
#980000
0%
#985000
b1100010 "
b1100010 9
b1100010 @
1%
#990000
0%
#995000
b1100011 "
b1100011 9
b1100011 @
1%
#1000000
0%
#1005000
b1100100 "
b1100100 9
b1100100 @
1%
