app/05/pocoisa/rfile.v
`include "def.h"
module rfile (
 input clk,
 input [`REG_W-1:0] aadr, badr, cadr,
 output [`DATA_W-1:0] a, b,
 input [`DATA_W-1:0] c, 
 input we);

	reg [`DATA_W-1:0] r0, r1, r2, r3, r4, r5, r6, r7;

	assign a = aadr == 0 ? r0:
		aadr == 1 ? r1:
		aadr == 2 ? r2:
		aadr == 3 ? r3:
		aadr == 4 ? r4:
		aadr == 5 ? r5:
		aadr == 6 ? r6: r7;
	assign b = badr == 0 ? r0:
		badr == 1 ? r1:
		badr == 2 ? r2:
		badr == 3 ? r3:
		badr == 4 ? r4:
		badr == 5 ? r5:
		badr == 6 ? r6: r7;

	always @(posedge clk) begin
		if(we) 
		case(cadr) 
			0: r0 <= c;
			1: r1 <= c;
			2: r2 <= c;
			3: r3 <= c;
			4: r4 <= c;
			5: r5 <= c;
			6: r6 <= c;
			default: r7 <= c;
		endcase
	end

endmodule

app/02/alu0.v
module alu (
    input  [15:0] a,
    b,
    input  [ 2:0] s,
    output [15:0] y
);

  assign y = s==3'b000 ? a:
             s==3'b001 ? b:
             s==3'b010 ? a & b:
             s==3'b011 ? a | b:
             s==3'b100 ? a << 1:
             s==3'b101 ? a >> 1:
             s==3'b110 ? a + b : a - b ;
endmodule

app/07/jal/poco.v
`include "def.h"
module poco(
input clk, rst_n,
input [`DATA_W-1:0] idatain,
input [`DATA_W-1:0] ddatain,
output [`DATA_W-1:0] iaddr, daddr,
output [`DATA_W-1:0] ddataout,
output we);

reg [`DATA_W-1:0] pc;
wire [`DATA_W-1:0] rf_a, rf_b, rf_c;
wire [`DATA_W-1:0] alu_b, alu_y;
wire [`OPCODE_W-1:0] opcode;
wire [`OPCODE_W-1:0] func;
wire [`REG_W-1:0] rs, rd, cadr;
wire [`SEL_W-1:0] com;
wire [`IMM_W-1:0] imm;
wire rwe;
wire st_op, bez_op, bnz_op, bmi_op, bpl_op, addi_op, ld_op, alu_op;
wire ldi_op, ldiu_op, ldhi_op, addiu_op, jmp_op, jal_op, jr_op, jalr_op;

assign ddataout = rf_a;
assign iaddr = pc;
assign daddr = rf_b;

assign {opcode, rd, rs, func} = idatain;
assign imm = idatain[`IMM_W-1:0];

// Decorder
assign st_op = (opcode == `OP_REG) & (func == `F_ST);
assign ld_op = (opcode == `OP_REG) & (func == `F_LD);
assign jr_op = (opcode == `OP_REG) & (func == `F_JR);
assign jalr_op = (opcode == `OP_REG) & (func == `F_JALR);
assign alu_op = (opcode == `OP_REG) & (func[4:3] == 2'b00);
assign ldi_op = (opcode == `OP_LDI);
assign ldiu_op = (opcode == `OP_LDIU);
assign addi_op = (opcode == `OP_ADDI);
assign addiu_op = (opcode == `OP_ADDIU);
assign ldhi_op = (opcode == `OP_LDHI);
assign bez_op = (opcode == `OP_BEZ);
assign bnz_op = (opcode == `OP_BNZ);
assign bpl_op = (opcode == `OP_BPL);
assign bmi_op = (opcode == `OP_BMI);
assign jmp_op = (opcode == `OP_JMP);
assign jal_op = (opcode == `OP_JAL);

assign we = st_op;

assign alu_b = (addi_op | ldi_op) ? {{8{imm[7]}},imm} :
		(addiu_op | ldiu_op) ? {8'b0,imm} :
		(ldhi_op) ? {imm, 8'b0} : rf_b;

assign com = (addi_op | addiu_op ) ? `ALU_ADD: 
		(ldi_op | ldiu_op | ldhi_op) ? `ALU_THB: func[`SEL_W-1:0];

assign rf_c = ld_op  ? ddatain : jal_op ? pc+1 : alu_y;
assign rwe = ld_op  | alu_op | ldi_op | ldiu_op | addi_op | addiu_op | ldhi_op
		| jal_op ;

assign cadr = jal_op ? 3'b111 : rd;

alu alu_1(.a(rf_a), .b(alu_b), .s(com), .y(alu_y));

rfile rfile_1(.clk(clk), .a(rf_a), .aadr(rd), .b(rf_b), .badr(rs), 
	.c(rf_c), .cadr(cadr), .we(rwe));

always @(posedge clk or negedge rst_n) 
begin 
   if(!rst_n) pc <= 0;
   else if ((bez_op & rf_a == 16'b0 ) | (bnz_op & rf_a != 16'b0) |
		(bpl_op & ~rf_a[15]) | (bmi_op & rf_a[15]))
     pc <= pc +{{8{imm[7]}},imm}+1 ;
   else if (jmp_op | jal_op)
    pc <= pc + {{5{idatain[10]}},idatain[10:0]}+1;
   else if(jr_op)
    pc <= rf_a;
   else 
     pc <= pc+1;
end

endmodule

app/05/pocoisa/test_poco.v
/* test bench */
`timescale 1ns/1ps
`include "def.h"
module test;
parameter STEP = 10;
   reg clk, rst_n;
   wire [`DATA_W-1:0] ddataout ;
   wire [`DATA_W-1:0] daddr, iaddr;
   wire we;
   reg [`DATA_W-1:0] dmem [0:`DEPTH-1];
   reg [`DATA_W-1:0] imem [0:`DEPTH-1];

   always #(STEP/2) begin
            clk <= ~clk;
   end

   poco poco_1(.clk(clk), .rst_n(rst_n), .idatain(imem[iaddr]),
               .ddatain(dmem[daddr]), .iaddr(iaddr), .daddr(daddr),
               .ddataout(ddataout), .we(we));

   always @(posedge clk) 
   begin 
      if(we) dmem[daddr] <= ddataout;
   end

   initial begin
      $dumpfile("poco.vcd");
      $dumpvars(0,test);
      $readmemh("dmem.dat", dmem);
      $readmemb("imem.dat", imem);
      clk <= `DISABLE;
      rst_n <= `ENABLE_N;
   #(STEP*1/4)
   #STEP
      rst_n <= `DISABLE_N;
   #(STEP*100)            
   $finish;
   end

   always @(negedge clk) begin
      $display("pc:%h idatain:%b ", poco_1.pc, poco_1.idatain);
      $display("reg:%h %h %h %h %h %h %h %h", 
	poco_1.rfile_1.r0, poco_1.rfile_1.r1, poco_1.rfile_1.r2,
	poco_1.rfile_1.r3, poco_1.rfile_1.r4, poco_1.rfile_1.r5,
	poco_1.rfile_1.r6, poco_1.rfile_1.r7);
      $display("dmem:%h %h %h %h", dmem[0], dmem[1], dmem[2], dmem[3]);
   end
endmodule

app/07/jal/poco.vcd
$date
	Tue Nov  8 02:50:52 2022
$end
$version
	Icarus Verilog
$end
$timescale
	1ps
$end
$scope module test $end
$var wire 1 ! we $end
$var wire 16 " iaddr [15:0] $end
$var wire 16 # ddataout [15:0] $end
$var wire 16 $ daddr [15:0] $end
$var reg 1 % clk $end
$var reg 1 & rst_n $end
$scope module poco_1 $end
$var wire 1 ' alu_op $end
$var wire 1 % clk $end
$var wire 16 ( daddr [15:0] $end
$var wire 16 ) ddatain [15:0] $end
$var wire 16 * ddataout [15:0] $end
$var wire 16 + iaddr [15:0] $end
$var wire 16 , idatain [15:0] $end
$var wire 1 - jalr_op $end
$var wire 1 . jr_op $end
$var wire 1 / ld_op $end
$var wire 1 & rst_n $end
$var wire 1 0 rwe $end
$var wire 1 1 st_op $end
$var wire 1 ! we $end
$var wire 3 2 rs [2:0] $end
$var wire 16 3 rf_c [15:0] $end
$var wire 16 4 rf_b [15:0] $end
$var wire 16 5 rf_a [15:0] $end
$var wire 3 6 rd [2:0] $end
$var wire 5 7 opcode [4:0] $end
$var wire 1 8 ldiu_op $end
$var wire 1 9 ldi_op $end
$var wire 1 : ldhi_op $end
$var wire 1 ; jmp_op $end
$var wire 1 < jal_op $end
$var wire 8 = imm [7:0] $end
$var wire 5 > func [4:0] $end
$var wire 3 ? com [2:0] $end
$var wire 3 @ cadr [2:0] $end
$var wire 1 A bpl_op $end
$var wire 1 B bnz_op $end
$var wire 1 C bmi_op $end
$var wire 1 D bez_op $end
$var wire 16 E alu_y [15:0] $end
$var wire 16 F alu_b [15:0] $end
$var wire 1 G addiu_op $end
$var wire 1 H addi_op $end
$var reg 16 I pc [15:0] $end
$scope module alu_1 $end
$var wire 16 J b [15:0] $end
$var wire 3 K s [2:0] $end
$var wire 16 L y [15:0] $end
$var wire 16 M a [15:0] $end
$upscope $end
$scope module rfile_1 $end
$var wire 3 N aadr [2:0] $end
$var wire 3 O badr [2:0] $end
$var wire 16 P c [15:0] $end
$var wire 3 Q cadr [2:0] $end
$var wire 1 % clk $end
$var wire 1 0 we $end
$var wire 16 R b [15:0] $end
$var wire 16 S a [15:0] $end
$var reg 16 T r0 [15:0] $end
$var reg 16 U r1 [15:0] $end
$var reg 16 V r2 [15:0] $end
$var reg 16 W r3 [15:0] $end
$var reg 16 X r4 [15:0] $end
$var reg 16 Y r5 [15:0] $end
$var reg 16 Z r6 [15:0] $end
$var reg 16 [ r7 [15:0] $end
$upscope $end
$upscope $end
$upscope $end
$enddefinitions $end
#0
$dumpvars
bx [
bx Z
bx Y
bx X
bx W
bx V
bx U
bx T
bx S
bx R
b0 Q
b0 P
b0 O
b0 N
bx M
b0 L
b1 K
b0 J
b0 I
0H
0G
b0 F
b0 E
0D
0C
0B
0A
b0 @
b1 ?
b0 >
b0 =
0<
0;
0:
09
18
b1001 7
b0 6
bx 5
bx 4
b0 3
b0 2
01
10
0/
0.
0-
b100100000000000 ,
b0 +
bx *
bx )
bx (
0'
0&
0%
bx $
bx #
b0 "
0!
$end
#5000
b0 #
b0 *
b0 5
b0 M
b0 S
b11 )
b0 $
b0 (
b0 4
b0 R
b0 T
1%
#10000
0%
#12000
1&
#15000
10
b0 E
b0 L
b11 3
b11 P
b0 F
b0 J
b1 @
b1 Q
bx #
bx *
bx 5
bx M
bx S
1/
08
b0 7
b1 6
b1 N
b1001 >
b1001 =
b100001001 ,
b1 "
b1 +
b1 I
1%
#20000
0%
#25000
b11 E
b11 L
b11 F
b11 J
b11 3
b11 P
1'
b10 @
b10 Q
b0 )
b11 $
b11 (
b11 4
b11 R
0/
b10 6
b10 N
b1 2
b1 O
b1 >
b100001 =
b11 U
b1000100001 ,
b10 "
b10 +
b10 I
1%
#30000
0%
#35000
b0 E
b0 L
b0 F
b0 J
b100 ?
b100 K
b100 3
b100 P
0'
b111 @
b111 Q
b0 #
b0 *
b0 5
b0 M
b0 S
b11 )
b0 $
b0 (
b0 4
b0 R
1<
b10101 7
b0 6
b0 N
b0 2
b0 O
b100 >
b100 =
b11 V
b1010100000000100 ,
b11 "
b11 +
b11 I
1%
#40000
0%
#45000
b0 E
b0 L
b1 ?
b1 K
b0 3
b0 P
b11 @
b11 Q
10
bx #
bx *
bx 5
bx M
bx S
18
0<
b1001 7
b11 6
b11 N
b0 >
b0 =
b100 [
b100101100000000 ,
b1000 "
b1000 +
b1000 I
1%
#50000
0%
#55000
b11 3
b11 P
10
b110 ?
b110 K
b11 E
b11 L
b0 #
b0 *
b0 5
b0 M
b0 S
b11 F
b11 J
1'
b0 )
b11 $
b11 (
b11 4
b11 R
08
b0 7
b1 2
b1 O
b110 >
b100110 =
b0 W
b1100100110 ,
b1001 "
b1001 +
b1001 I
1%
#60000
0%
#65000
b10 3
b10 P
b10 E
b10 L
b11 #
b11 *
b11 5
b11 M
b11 S
b1111111111111111 F
b1111111111111111 J
bx )
b100 $
b100 (
b100 4
b100 R
0'
b10 @
b10 Q
1H
b1100 7
b10 6
b10 N
b111 2
b111 O
b11111 >
b11111111 =
b11 W
b110001011111111 ,
b1010 "
b1010 +
b1010 I
1%
#70000
0%
#75000
b1 3
b1 P
b1 E
b1 L
00
b10 #
b10 *
b10 5
b10 M
b10 S
b101 ?
b101 K
b100 F
b100 J
0H
1B
b10001 7
b11101 >
b11111101 =
b10 V
b1000101011111101 ,
b1011 "
b1011 +
b1011 I
1%
#80000
0%
#85000
b110 3
b110 P
b110 E
b110 L
10
b11 F
b11 J
b11 #
b11 *
b11 5
b11 M
b11 S
b110 ?
b110 K
b0 )
b11 $
b11 (
b11 4
b11 R
1'
b11 @
b11 Q
0B
b0 7
b11 6
b11 N
b1 2
b1 O
b110 >
b100110 =
b1100100110 ,
b1001 "
b1001 +
b1001 I
1%
#90000
0%
#95000
b1 3
b1 P
b1 E
b1 L
b10 #
b10 *
b10 5
b10 M
b10 S
b1111111111111111 F
b1111111111111111 J
bx )
b100 $
b100 (
b100 4
b100 R
0'
b10 @
b10 Q
1H
b1100 7
b10 6
b10 N
b111 2
b111 O
b11111 >
b11111111 =
b110 W
b110001011111111 ,
b1010 "
b1010 +
b1010 I
1%
#100000
0%
#105000
b0 3
b0 P
b0 E
b0 L
00
b1 #
b1 *
b1 5
b1 M
b1 S
b101 ?
b101 K
b100 F
b100 J
0H
1B
b10001 7
b11101 >
b11111101 =
b1 V
b1000101011111101 ,
b1011 "
b1011 +
b1011 I
1%
#110000
0%
#115000
b1001 3
b1001 P
b1001 E
b1001 L
10
b11 F
b11 J
b110 #
b110 *
b110 5
b110 M
b110 S
b110 ?
b110 K
b0 )
b11 $
b11 (
b11 4
b11 R
1'
b11 @
b11 Q
0B
b0 7
b11 6
b11 N
b1 2
b1 O
b110 >
b100110 =
b1100100110 ,
b1001 "
b1001 +
b1001 I
1%
#120000
0%
#125000
b0 3
b0 P
b0 E
b0 L
b1 #
b1 *
b1 5
b1 M
b1 S
b1111111111111111 F
b1111111111111111 J
bx )
b100 $
b100 (
b100 4
b100 R
0'
b10 @
b10 Q
1H
b1100 7
b10 6
b10 N
b111 2
b111 O
b11111 >
b11111111 =
b1001 W
b110001011111111 ,
b1010 "
b1010 +
b1010 I
1%
#130000
0%
#135000
00
b0 #
b0 *
b0 5
b0 M
b0 S
b101 ?
b101 K
b100 F
b100 J
0H
1B
b10001 7
b11101 >
b11111101 =
b0 V
b1000101011111101 ,
b1011 "
b1011 +
b1011 I
1%
#140000
0%
#145000
b0 F
b0 J
b100 #
b100 *
b100 5
b100 M
b100 S
b10 ?
b10 K
b111 @
b111 Q
b11 )
b0 $
b0 (
b0 4
b0 R
1.
0B
b0 7
b111 6
b111 N
b0 2
b0 O
b1010 >
b1010 =
b11100001010 ,
b1100 "
b1100 +
b1100 I
1%
#150000
0%
#155000
10
b1001 3
b1001 P
b1001 E
b1001 L
b1001 F
b1001 J
b0 #
b0 *
b0 5
b0 M
b0 S
b1 ?
b1 K
1'
b10 @
b10 Q
bx )
b1001 $
b1001 (
b1001 4
b1001 R
0.
b10 6
b10 N
b11 2
b11 O
b1 >
b1100001 =
b1001100001 ,
b100 "
b100 +
b100 I
1%
#160000
0%
#165000
b0 E
b0 L
b0 F
b0 J
b10 ?
b10 K
b110 3
b110 P
0'
b111 @
b111 Q
b11 )
b0 $
b0 (
b0 4
b0 R
1<
b10101 7
b0 6
b0 N
b0 2
b0 O
b10 >
b10 =
b1001 V
b1010100000000010 ,
b101 "
b101 +
b101 I
1%
#170000
0%
#175000
b0 E
b0 L
b1 ?
b1 K
b0 3
b0 P
b11 @
b11 Q
10
b1001 #
b1001 *
b1001 5
b1001 M
b1001 S
18
0<
b1001 7
b11 6
b11 N
b0 >
b0 =
b110 [
b100101100000000 ,
b1000 "
b1000 +
b1000 I
1%
#180000
0%
#185000
b11 3
b11 P
10
b110 ?
b110 K
b11 E
b11 L
b0 #
b0 *
b0 5
b0 M
b0 S
b11 F
b11 J
1'
b0 )
b11 $
b11 (
b11 4
b11 R
08
b0 7
b1 2
b1 O
b110 >
b100110 =
b0 W
b1100100110 ,
b1001 "
b1001 +
b1001 I
1%
#190000
0%
#195000
b1000 3
b1000 P
b1000 E
b1000 L
b1001 #
b1001 *
b1001 5
b1001 M
b1001 S
b1111111111111111 F
b1111111111111111 J
bx )
b110 $
b110 (
b110 4
b110 R
0'
b10 @
b10 Q
1H
b1100 7
b10 6
b10 N
b111 2
b111 O
b11111 >
b11111111 =
b11 W
b110001011111111 ,
b1010 "
b1010 +
b1010 I
1%
#200000
0%
#205000
b100 3
b100 P
b100 E
b100 L
00
b1000 #
b1000 *
b1000 5
b1000 M
b1000 S
b101 ?
b101 K
b110 F
b110 J
0H
1B
b10001 7
b11101 >
b11111101 =
b1000 V
b1000101011111101 ,
b1011 "
b1011 +
b1011 I
1%
#210000
0%
#215000
b110 3
b110 P
b110 E
b110 L
10
b11 F
b11 J
b11 #
b11 *
b11 5
b11 M
b11 S
b110 ?
b110 K
b0 )
b11 $
b11 (
b11 4
b11 R
1'
b11 @
b11 Q
0B
b0 7
b11 6
b11 N
b1 2
b1 O
b110 >
b100110 =
b1100100110 ,
b1001 "
b1001 +
b1001 I
1%
#220000
0%
#225000
b111 3
b111 P
b111 E
b111 L
b1000 #
b1000 *
b1000 5
b1000 M
b1000 S
b1111111111111111 F
b1111111111111111 J
bx )
b110 $
b110 (
b110 4
b110 R
0'
b10 @
b10 Q
1H
b1100 7
b10 6
b10 N
b111 2
b111 O
b11111 >
b11111111 =
b110 W
b110001011111111 ,
b1010 "
b1010 +
b1010 I
1%
#230000
0%
#235000
b11 3
b11 P
b11 E
b11 L
00
b111 #
b111 *
b111 5
b111 M
b111 S
b101 ?
b101 K
b110 F
b110 J
0H
1B
b10001 7
b11101 >
b11111101 =
b111 V
b1000101011111101 ,
b1011 "
b1011 +
b1011 I
1%
#240000
0%
#245000
b1001 3
b1001 P
b1001 E
b1001 L
10
b11 F
b11 J
b110 #
b110 *
b110 5
b110 M
b110 S
b110 ?
b110 K
b0 )
b11 $
b11 (
b11 4
b11 R
1'
b11 @
b11 Q
0B
b0 7
b11 6
b11 N
b1 2
b1 O
b110 >
b100110 =
b1100100110 ,
b1001 "
b1001 +
b1001 I
1%
#250000
0%
#255000
b110 3
b110 P
b110 E
b110 L
b111 #
b111 *
b111 5
b111 M
b111 S
b1111111111111111 F
b1111111111111111 J
bx )
b110 $
b110 (
b110 4
b110 R
0'
b10 @
b10 Q
1H
b1100 7
b10 6
b10 N
b111 2
b111 O
b11111 >
b11111111 =
b1001 W
b110001011111111 ,
b1010 "
b1010 +
b1010 I
1%
#260000
0%
#265000
b11 3
b11 P
b11 E
b11 L
00
b110 #
b110 *
b110 5
b110 M
b110 S
b101 ?
b101 K
b110 F
b110 J
0H
1B
b10001 7
b11101 >
b11111101 =
b110 V
b1000101011111101 ,
b1011 "
b1011 +
b1011 I
1%
#270000
0%
#275000
b1100 3
b1100 P
b1100 E
b1100 L
10
b11 F
b11 J
b1001 #
b1001 *
b1001 5
b1001 M
b1001 S
b110 ?
b110 K
b0 )
b11 $
b11 (
b11 4
b11 R
1'
b11 @
b11 Q
0B
b0 7
b11 6
b11 N
b1 2
b1 O
b110 >
b100110 =
b1100100110 ,
b1001 "
b1001 +
b1001 I
1%
#280000
0%
#285000
b101 3
b101 P
b101 E
b101 L
b110 #
b110 *
b110 5
b110 M
b110 S
b1111111111111111 F
b1111111111111111 J
bx )
b110 $
b110 (
b110 4
b110 R
0'
b10 @
b10 Q
1H
b1100 7
b10 6
b10 N
b111 2
b111 O
b11111 >
b11111111 =
b1100 W
b110001011111111 ,
b1010 "
b1010 +
b1010 I
1%
#290000
0%
#295000
b10 3
b10 P
b10 E
b10 L
00
b101 #
b101 *
b101 5
b101 M
b101 S
b101 ?
b101 K
b110 F
b110 J
0H
1B
b10001 7
b11101 >
b11111101 =
b101 V
b1000101011111101 ,
b1011 "
b1011 +
b1011 I
1%
#300000
0%
#305000
b1111 3
b1111 P
b1111 E
b1111 L
10
b11 F
b11 J
b1100 #
b1100 *
b1100 5
b1100 M
b1100 S
b110 ?
b110 K
b0 )
b11 $
b11 (
b11 4
b11 R
1'
b11 @
b11 Q
0B
b0 7
b11 6
b11 N
b1 2
b1 O
b110 >
b100110 =
b1100100110 ,
b1001 "
b1001 +
b1001 I
1%
#310000
0%
#315000
b100 3
b100 P
b100 E
b100 L
b101 #
b101 *
b101 5
b101 M
b101 S
b1111111111111111 F
b1111111111111111 J
bx )
b110 $
b110 (
b110 4
b110 R
0'
b10 @
b10 Q
1H
b1100 7
b10 6
b10 N
b111 2
b111 O
b11111 >
b11111111 =
b1111 W
b110001011111111 ,
b1010 "
b1010 +
b1010 I
1%
#320000
0%
#325000
b10 3
b10 P
b10 E
b10 L
00
b100 #
b100 *
b100 5
b100 M
b100 S
b101 ?
b101 K
b110 F
b110 J
0H
1B
b10001 7
b11101 >
b11111101 =
b100 V
b1000101011111101 ,
b1011 "
b1011 +
b1011 I
1%
#330000
0%
#335000
b10010 3
b10010 P
b10010 E
b10010 L
10
b11 F
b11 J
b1111 #
b1111 *
b1111 5
b1111 M
b1111 S
b110 ?
b110 K
b0 )
b11 $
b11 (
b11 4
b11 R
1'
b11 @
b11 Q
0B
b0 7
b11 6
b11 N
b1 2
b1 O
b110 >
b100110 =
b1100100110 ,
b1001 "
b1001 +
b1001 I
1%
#340000
0%
#345000
b11 3
b11 P
b11 E
b11 L
b100 #
b100 *
b100 5
b100 M
b100 S
b1111111111111111 F
b1111111111111111 J
bx )
b110 $
b110 (
b110 4
b110 R
0'
b10 @
b10 Q
1H
b1100 7
b10 6
b10 N
b111 2
b111 O
b11111 >
b11111111 =
b10010 W
b110001011111111 ,
b1010 "
b1010 +
b1010 I
1%
#350000
0%
#355000
b1 3
b1 P
b1 E
b1 L
00
b11 #
b11 *
b11 5
b11 M
b11 S
b101 ?
b101 K
b110 F
b110 J
0H
1B
b10001 7
b11101 >
b11111101 =
b11 V
b1000101011111101 ,
b1011 "
b1011 +
b1011 I
1%
#360000
0%
#365000
b10101 3
b10101 P
b10101 E
b10101 L
10
b11 F
b11 J
b10010 #
b10010 *
b10010 5
b10010 M
b10010 S
b110 ?
b110 K
b0 )
b11 $
b11 (
b11 4
b11 R
1'
b11 @
b11 Q
0B
b0 7
b11 6
b11 N
b1 2
b1 O
b110 >
b100110 =
b1100100110 ,
b1001 "
b1001 +
b1001 I
1%
#370000
0%
#375000
b10 3
b10 P
b10 E
b10 L
b11 #
b11 *
b11 5
b11 M
b11 S
b1111111111111111 F
b1111111111111111 J
bx )
b110 $
b110 (
b110 4
b110 R
0'
b10 @
b10 Q
1H
b1100 7
b10 6
b10 N
b111 2
b111 O
b11111 >
b11111111 =
b10101 W
b110001011111111 ,
b1010 "
b1010 +
b1010 I
1%
#380000
0%
#385000
b1 3
b1 P
b1 E
b1 L
00
b10 #
b10 *
b10 5
b10 M
b10 S
b101 ?
b101 K
b110 F
b110 J
0H
1B
b10001 7
b11101 >
b11111101 =
b10 V
b1000101011111101 ,
b1011 "
b1011 +
b1011 I
1%
#390000
0%
#395000
b11000 3
b11000 P
b11000 E
b11000 L
10
b11 F
b11 J
b10101 #
b10101 *
b10101 5
b10101 M
b10101 S
b110 ?
b110 K
b0 )
b11 $
b11 (
b11 4
b11 R
1'
b11 @
b11 Q
0B
b0 7
b11 6
b11 N
b1 2
b1 O
b110 >
b100110 =
b1100100110 ,
b1001 "
b1001 +
b1001 I
1%
#400000
0%
#405000
b1 3
b1 P
b1 E
b1 L
b10 #
b10 *
b10 5
b10 M
b10 S
b1111111111111111 F
b1111111111111111 J
bx )
b110 $
b110 (
b110 4
b110 R
0'
b10 @
b10 Q
1H
b1100 7
b10 6
b10 N
b111 2
b111 O
b11111 >
b11111111 =
b11000 W
b110001011111111 ,
b1010 "
b1010 +
b1010 I
1%
#410000
0%
#415000
b0 3
b0 P
b0 E
b0 L
00
b1 #
b1 *
b1 5
b1 M
b1 S
b101 ?
b101 K
b110 F
b110 J
0H
1B
b10001 7
b11101 >
b11111101 =
b1 V
b1000101011111101 ,
b1011 "
b1011 +
b1011 I
1%
#420000
0%
#425000
b11011 3
b11011 P
b11011 E
b11011 L
10
b11 F
b11 J
b11000 #
b11000 *
b11000 5
b11000 M
b11000 S
b110 ?
b110 K
b0 )
b11 $
b11 (
b11 4
b11 R
1'
b11 @
b11 Q
0B
b0 7
b11 6
b11 N
b1 2
b1 O
b110 >
b100110 =
b1100100110 ,
b1001 "
b1001 +
b1001 I
1%
#430000
0%
#435000
b0 3
b0 P
b0 E
b0 L
b1 #
b1 *
b1 5
b1 M
b1 S
b1111111111111111 F
b1111111111111111 J
bx )
b110 $
b110 (
b110 4
b110 R
0'
b10 @
b10 Q
1H
b1100 7
b10 6
b10 N
b111 2
b111 O
b11111 >
b11111111 =
b11011 W
b110001011111111 ,
b1010 "
b1010 +
b1010 I
1%
#440000
0%
#445000
00
b0 #
b0 *
b0 5
b0 M
b0 S
b101 ?
b101 K
b110 F
b110 J
0H
1B
b10001 7
b11101 >
b11111101 =
b0 V
b1000101011111101 ,
b1011 "
b1011 +
b1011 I
1%
#450000
0%
#455000
b0 F
b0 J
b110 #
b110 *
b110 5
b110 M
b110 S
b10 ?
b10 K
b111 @
b111 Q
b11 )
b0 $
b0 (
b0 4
b0 R
1.
0B
b0 7
b111 6
b111 N
b0 2
b0 O
b1010 >
b1010 =
b11100001010 ,
b1100 "
b1100 +
b1100 I
1%
#460000
0%
#465000
b11011 3
b11011 P
b11011 #
b11011 *
b11011 5
b11011 M
b11011 S
b11011 E
b11011 L
b0 ?
b0 K
b11 @
b11 Q
1!
11
0.
b11 6
b11 N
b1000 >
b1000 =
b1100001000 ,
b110 "
b110 +
b110 I
1%
#470000
0%
#475000
b0 3
b0 P
b0 E
b0 L
b110 #
b110 *
b110 5
b110 M
b110 S
b110 F
b110 J
b111 ?
b111 K
b111 @
b111 Q
b110 $
b110 (
b110 4
b110 R
0!
01
1;
b10100 7
b111 6
b111 N
b111 2
b111 O
b11111 >
b11111111 =
bx )
b1010011111111111 ,
b111 "
b111 +
b111 I
1%
