app/04/4kai/alu.v
`include "def.h"

module alu (
  input [`DATA_W-1:0] a, b, 
  input [`SEL_W-1:0] s,
  output [`DATA_W-1:0] y );
  assign y = s==`ALU_THA ? a:
             s==`ALU_THB ? b:
             s==`ALU_AND ? a & b: 
             s==`ALU_OR ? a | b: 
             s==`ALU_SL ? a<<1: 
             s==`ALU_SR ? a>>1: 
             s==`ALU_ADD ? a + b: a - b ;
endmodule

app/04/4kai/amb.v
`include "def.h"
module amb(
input clk, input rst_n,
input [`OPCODE_W-1:0] opcode,
input [`ADDR_W-1:0] operand,
input [`DATA_W-1:0] ddatain,
output we,
output reg [`ADDR_W-1:0] pc,
output reg [`DATA_W-1:0] accum);

wire [`DATA_W-1:0] alu_y;
wire op_st, op_bez, op_bnz;

assign op_st = opcode == `OP_ST;
assign op_bez = opcode == `OP_BEZ;
assign op_bnz = opcode == `OP_BNZ;

assign we = op_st;
alu alu_1(.a(accum), .b(ddatain), .s(opcode[`SEL_W-1:0]), .y(alu_y));

always @(posedge clk or negedge rst_n)
begin
   if(!rst_n) pc <= 0;
   else if (op_bez & (accum == 0) | op_bnz & (accum != 0))
        pc <= operand;
   else pc <= pc + 1;
end

always @(posedge clk or negedge rst_n)
begin
    if(!rst_n) accum <= 0;
    else if(!op_st & !op_bez & !op_bnz ) accum <= alu_y;
end

endmodule

app/04/4kai/test_amb.v
/* test bench */
`timescale 1ns/1ps
`include "def.h"
module test;
parameter STEP = 10;
   reg clk, rst_n;
   wire [`DATA_W-1:0] ddataout ;
   wire [`ADDR_W-1:0] pcout;
   wire [`OPCODE_W-1:0] opcode;
   wire [`ADDR_W-1:0] operand;
   wire we;

   reg [`DATA_W-1:0] dmem [`DEPTH-1:0];
   reg [`INST_W-1:0] imem [`DEPTH-1:0];

   assign {opcode, operand} = imem[pcout];

   always #(STEP/2) begin
            clk <= ~clk;
   end
   always @(posedge clk)
        if (we) dmem[operand] = ddataout;

   amb amb_1(.clk(clk), .rst_n(rst_n), .pc(pcout), .accum(ddataout),
        .opcode(opcode), .operand(operand), .we(we), .ddatain(dmem[operand]) );

   initial begin
      $dumpfile("amb.vcd");
      $dumpvars(0,test);
      $readmemh("dmem.dat", dmem);
      $readmemb("imem.dat", imem);
      clk <= `DISABLE;
      rst_n <= `ENABLE_N;
   #(STEP*1/4)
   #STEP
      rst_n <= `DISABLE_N;
   #(STEP*40)
   $finish;
   end

   always @(negedge clk) begin
      $display("pc:%h inst:%b acc:%h", pcout, {opcode,operand}, amb_1.accum);
      $display("dmem:%h %h %h %h", dmem[0], dmem[1], dmem[2], dmem[3]);
   end
endmodule

app/04/4kai/amb.vcd
$date
	Tue Oct 18 03:12:36 2022
$end
$version
	Icarus Verilog
$end
$timescale
	1ps
$end
$scope module test $end
$var wire 1 ! we $end
$var wire 8 " pcout [7:0] $end
$var wire 8 # operand [7:0] $end
$var wire 4 $ opcode [3:0] $end
$var wire 16 % ddataout [15:0] $end
$var reg 1 & clk $end
$var reg 1 ' rst_n $end
$scope module amb_1 $end
$var wire 1 & clk $end
$var wire 16 ( ddatain [15:0] $end
$var wire 4 ) opcode [3:0] $end
$var wire 8 * operand [7:0] $end
$var wire 1 ' rst_n $end
$var wire 1 ! we $end
$var wire 1 + op_st $end
$var wire 1 , op_bnz $end
$var wire 1 - op_bez $end
$var wire 16 . alu_y [15:0] $end
$var reg 16 / accum [15:0] $end
$var reg 8 0 pc [7:0] $end
$scope module alu_1 $end
$var wire 16 1 a [15:0] $end
$var wire 16 2 b [15:0] $end
$var wire 3 3 s [2:0] $end
$var wire 16 4 y [15:0] $end
$upscope $end
$upscope $end
$upscope $end
$enddefinitions $end
#0
$dumpvars
b101 4
b1 3
b101 2
b0 1
b0 0
b0 /
b101 .
0-
0,
0+
b1 *
b1 )
b101 (
0'
0&
b0 %
b1 $
b1 #
b0 "
0!
$end
#5000
1&
#10000
0&
#12000
1'
#15000
b0 3
1!
1+
b1000 $
b1000 )
b0 (
b0 2
b0 #
b0 *
b1 "
b1 0
b101 %
b101 /
b101 1
1&
#20000
0&
#25000
b1 3
0!
0+
b1 $
b1 )
b1 #
b1 *
b10 "
b10 0
b101 (
b101 2
1&
#30000
0&
#35000
b100 .
b100 4
b111 3
b111 $
b111 )
b1 (
b1 2
b11 #
b11 *
b11 "
b11 0
1&
#40000
0&
#45000
b0 3
1!
1+
b1000 $
b1000 )
b101 (
b101 2
b1 #
b1 *
b100 %
b100 /
b100 1
b100 "
b100 0
1&
#50000
0&
#55000
b1001 .
b1001 4
b110 3
0!
0+
b110 $
b110 )
b0 #
b0 *
b101 "
b101 0
b101 (
b101 2
1&
#60000
0&
#65000
b0 3
1!
1+
b1000 $
b1000 )
b1001 %
b1001 /
b1001 1
b110 "
b110 0
1&
#70000
0&
#75000
b100 .
b100 4
b1 3
0!
0+
b1 $
b1 )
b1 #
b1 *
b111 "
b111 0
b100 (
b100 2
1&
#80000
0&
#85000
b0 .
b0 4
b10 3
1,
b1010 $
b1010 )
b11 (
b11 2
b10 #
b10 *
b100 %
b100 /
b100 1
b1000 "
b1000 0
1&
#90000
0&
#95000
b100 .
b100 4
b1 3
0,
b1 $
b1 )
b100 (
b100 2
b1 #
b1 *
b10 "
b10 0
1&
#100000
0&
#105000
b11 .
b11 4
b111 3
b111 $
b111 )
b1 (
b1 2
b11 #
b11 *
b11 "
b11 0
1&
#110000
0&
#115000
b0 3
1!
1+
b1000 $
b1000 )
b100 (
b100 2
b1 #
b1 *
b100 "
b100 0
b11 %
b11 /
b11 1
1&
#120000
0&
#125000
b1100 .
b1100 4
b110 3
0!
0+
b110 $
b110 )
b0 #
b0 *
b101 "
b101 0
b1001 (
b1001 2
1&
#130000
0&
#135000
b0 3
1!
1+
b1000 $
b1000 )
b110 "
b110 0
b1100 %
b1100 /
b1100 1
1&
#140000
0&
#145000
b11 .
b11 4
b1 3
0!
0+
b1 $
b1 )
b1 #
b1 *
b111 "
b111 0
b11 (
b11 2
1&
#150000
0&
#155000
b10 3
1,
b1010 $
b1010 )
b10 #
b10 *
b1000 "
b1000 0
b11 %
b11 /
b11 1
1&
#160000
0&
#165000
b1 3
0,
b1 $
b1 )
b1 #
b1 *
b10 "
b10 0
1&
#170000
0&
#175000
b10 .
b10 4
b111 3
b111 $
b111 )
b1 (
b1 2
b11 #
b11 *
b11 "
b11 0
1&
#180000
0&
#185000
b0 3
1!
1+
b1000 $
b1000 )
b11 (
b11 2
b1 #
b1 *
b10 %
b10 /
b10 1
b100 "
b100 0
1&
#190000
0&
#195000
b1110 .
b1110 4
b110 3
0!
0+
b110 $
b110 )
b0 #
b0 *
b101 "
b101 0
b1100 (
b1100 2
1&
#200000
0&
#205000
b0 3
1!
1+
b1000 $
b1000 )
b1110 %
b1110 /
b1110 1
b110 "
b110 0
1&
#210000
0&
#215000
b10 .
b10 4
b1 3
0!
0+
b1 $
b1 )
b1 #
b1 *
b111 "
b111 0
b10 (
b10 2
1&
#220000
0&
#225000
b10 .
b10 4
b10 3
1,
b1010 $
b1010 )
b11 (
b11 2
b10 #
b10 *
b10 %
b10 /
b10 1
b1000 "
b1000 0
1&
#230000
0&
#235000
b1 3
0,
b1 $
b1 )
b10 (
b10 2
b1 #
b1 *
b10 "
b10 0
1&
#240000
0&
#245000
b1 .
b1 4
b111 3
b111 $
b111 )
b1 (
b1 2
b11 #
b11 *
b11 "
b11 0
1&
#250000
0&
#255000
b0 3
1!
1+
b1000 $
b1000 )
b10 (
b10 2
b1 #
b1 *
b100 "
b100 0
b1 %
b1 /
b1 1
1&
#260000
0&
#265000
b1111 .
b1111 4
b110 3
0!
0+
b110 $
b110 )
b0 #
b0 *
b101 "
b101 0
b1110 (
b1110 2
1&
#270000
0&
#275000
b0 3
1!
1+
b1000 $
b1000 )
b110 "
b110 0
b1111 %
b1111 /
b1111 1
1&
#280000
0&
#285000
b1 .
b1 4
b1 3
0!
0+
b1 $
b1 )
b1 #
b1 *
b111 "
b111 0
b1 (
b1 2
1&
#290000
0&
#295000
b1 .
b1 4
b10 3
1,
b1010 $
b1010 )
b11 (
b11 2
b10 #
b10 *
b1000 "
b1000 0
b1 %
b1 /
b1 1
1&
#300000
0&
#305000
b1 3
0,
b1 $
b1 )
b1 (
b1 2
b1 #
b1 *
b10 "
b10 0
1&
#310000
0&
#315000
b0 .
b0 4
b111 3
b111 $
b111 )
b11 #
b11 *
b11 "
b11 0
1&
#320000
0&
#325000
b0 3
1!
1+
b1000 $
b1000 )
b1 #
b1 *
b0 %
b0 /
b0 1
b100 "
b100 0
1&
#330000
0&
#335000
b1111 .
b1111 4
b110 3
0!
0+
b110 $
b110 )
b0 #
b0 *
b101 "
b101 0
b1111 (
b1111 2
1&
#340000
0&
#345000
b0 3
1!
1+
b1000 $
b1000 )
b1111 %
b1111 /
b1111 1
b110 "
b110 0
1&
#350000
0&
#355000
b0 .
b0 4
b1 3
0!
0+
b1 $
b1 )
b0 (
b0 2
b1 #
b1 *
b111 "
b111 0
1&
#360000
0&
#365000
b0 .
b0 4
b10 3
1,
b1010 $
b1010 )
b11 (
b11 2
b10 #
b10 *
b0 %
b0 /
b0 1
b1000 "
b1000 0
1&
#370000
0&
#375000
bx .
bx 4
b1 3
1-
0,
b1001 $
b1001 )
bx (
bx 2
b1001 #
b1001 *
b1001 "
b1001 0
1&
