app/02/alu0.v
module alu (
    input  [15:0] a,
    b,
    input  [ 2:0] s,
    output [15:0] y
);

  assign y = s==3'b000 ? a:
             s==3'b001 ? b:
             s==3'b010 ? a & b:
             s==3'b011 ? a | b:
             s==3'b100 ? a << 1:
             s==3'b101 ? a >> 1:
             s==3'b110 ? a + b : a - b ;
endmodule

app/03/3kai/am.v
`include "def.h"
module am(
input clk, input rst_n,
input [`OPCODE_W-1:0] opcode,
input [`ADDR_W-1:0] operand,
input [`DATA_W-1:0] ddatain,
output we,
output [`ADDR_W-1:0] pcout,
output reg [`DATA_W-1:0] accum);

reg [`ADDR_W-1:0] pc;
wire [`DATA_W-1:0] alu_y;
wire op_st;

assign op_st = opcode == `OP_ST;

assign we = op_st;
assign pcout = pc;
alu alu_1(.a(accum), .b(ddatain), .s(opcode[`SEL_W-1:0]), .y(alu_y));

always @(posedge clk or negedge rst_n)
begin
   if(!rst_n) pc <= 0;
   else pc <= pc + 1;
end

always @(posedge clk or negedge rst_n)
begin
    if(!rst_n) accum <= 0;
    else if(!op_st ) accum <= alu_y;
end

endmodule

app/03/3kai/test_am.v
/* test bench */
`timescale 1ns/1ps
`include "def.h"
module test;
parameter STEP = 10;
   reg clk, rst_n;
   wire [`DATA_W-1:0] ddataout ;
   wire [`ADDR_W-1:0] pcout;
   wire [`OPCODE_W-1:0] opcode;
   wire [`ADDR_W-1:0] operand;
   wire we;

   reg [`DATA_W-1:0] dmem [`DEPTH-1:0];
   reg [`INST_W-1:0] imem [`DEPTH-1:0];

   assign opcode = imem[pcout][11:8];
   assign operand = imem[pcout][7:0];

   always #(STEP/2) begin
            clk <= ~clk;
   end
   always @(posedge clk)
        if (we) dmem[operand] = ddataout;

   am am0(.clk(clk), .rst_n(rst_n), .pcout(pcout), .accum(ddataout),
        .opcode(opcode), .operand(operand), .we(we), .ddatain(dmem[operand]) );

   initial begin
      $dumpfile("am.vcd");
      $dumpvars(0,test);
      $readmemh("dmem.dat", dmem);
      $readmemb("imem.dat", imem);
      clk <= `DISABLE;
      rst_n <= `ENABLE_N;
   #(STEP*1/4)
   #STEP
      rst_n <= `DISABLE_N;
   #(STEP*24)
   $finish;
   end

   always @(negedge clk) begin
      $display("pc:%h opcode:%b operand:%b acc:%h", pcout, opcode,operand, am0.accum);
      $display("dmem:%h %h %h %h", dmem[0], dmem[1], dmem[2], dmem[3]);
   end
endmodule

app/03/3kai/am.vcd
$date
	Tue Oct 11 03:28:30 2022
$end
$version
	Icarus Verilog
$end
$timescale
	1ps
$end
$scope module test $end
$var wire 1 ! we $end
$var wire 8 " pcout [7:0] $end
$var wire 8 # operand [7:0] $end
$var wire 4 $ opcode [3:0] $end
$var wire 16 % ddataout [15:0] $end
$var reg 1 & clk $end
$var reg 1 ' rst_n $end
$scope module am0 $end
$var wire 1 & clk $end
$var wire 16 ( ddatain [15:0] $end
$var wire 4 ) opcode [3:0] $end
$var wire 8 * operand [7:0] $end
$var wire 8 + pcout [7:0] $end
$var wire 1 ' rst_n $end
$var wire 1 ! we $end
$var wire 1 , op_st $end
$var wire 16 - alu_y [15:0] $end
$var reg 16 . accum [15:0] $end
$var reg 8 / pc [7:0] $end
$scope module alu_1 $end
$var wire 16 0 a [15:0] $end
$var wire 16 1 b [15:0] $end
$var wire 3 2 s [2:0] $end
$var wire 16 3 y [15:0] $end
$upscope $end
$upscope $end
$upscope $end
$enddefinitions $end
#0
$dumpvars
b101 3
b1 2
b101 1
b0 0
b0 /
b0 .
b101 -
0,
b0 +
b0 *
b1 )
b101 (
0'
0&
b0 %
b1 $
b0 #
b0 "
0!
$end
#5000
1&
#10000
0&
#12000
1'
#15000
b1000 -
b1000 3
b110 2
b11 (
b11 1
b1 #
b1 *
b110 $
b110 )
b1 "
b1 +
b1 /
b101 %
b101 .
b101 0
1&
#20000
0&
#25000
b0 2
b10 #
b10 *
1!
1,
b1000 $
b1000 )
b1000 %
b1000 .
b1000 0
b10 "
b10 +
b10 /
1&
#30000
0&
#35000
b101 -
b101 3
b1 2
b0 #
b0 *
0!
0,
b1 $
b1 )
b11 "
b11 +
b11 /
b101 (
b101 1
1&
#40000
0&
#45000
b10 -
b10 3
b111 2
b11 (
b11 1
b1 #
b1 *
b111 $
b111 )
b101 %
b101 .
b101 0
b100 "
b100 +
b100 /
1&
#50000
0&
#55000
b1010 -
b1010 3
b11 2
b1000 (
b1000 1
b10 #
b10 *
b11 $
b11 )
b101 "
b101 +
b101 /
b10 %
b10 .
b10 0
1&
#60000
0&
#65000
b0 2
1!
1,
b1000 $
b1000 )
b1010 %
b1010 .
b1010 0
b110 "
b110 +
b110 /
1&
#70000
0&
#75000
bx -
bx 3
bx 2
bx #
bx *
x!
x,
bx $
bx )
b111 "
b111 +
b111 /
bx (
bx 1
1&
#80000
0&
#85000
b1000 "
b1000 +
b1000 /
1&
#90000
0&
#95000
b1001 "
b1001 +
b1001 /
1&
#100000
0&
#105000
b1010 "
b1010 +
b1010 /
1&
#110000
0&
#115000
b1011 "
b1011 +
b1011 /
1&
#120000
0&
#125000
b1100 "
b1100 +
b1100 /
1&
#130000
0&
#135000
b1101 "
b1101 +
b1101 /
1&
#140000
0&
#145000
b1110 "
b1110 +
b1110 /
1&
#150000
0&
#155000
b1111 "
b1111 +
b1111 /
1&
#160000
0&
#165000
b10000 "
b10000 +
b10000 /
1&
#170000
0&
#175000
b10001 "
b10001 +
b10001 /
1&
#180000
0&
#185000
b10010 "
b10010 +
b10010 /
1&
#190000
0&
#195000
b10011 "
b10011 +
b10011 /
1&
#200000
0&
#205000
b10100 "
b10100 +
b10100 /
1&
#210000
0&
#215000
b10101 "
b10101 +
b10101 /
1&
#220000
0&
#225000
b10110 "
b10110 +
b10110 /
1&
#230000
0&
#235000
b10111 "
b10111 +
b10111 /
1&
#240000
0&
#245000
b11000 "
b11000 +
b11000 /
1&
