app/02/alu0.v
module alu (
    input  [15:0] a,
    b,
    input  [ 2:0] s,
    output [15:0] y
);

  assign y = s==3'b000 ? a:
             s==3'b001 ? b:
             s==3'b010 ? a & b:
             s==3'b011 ? a | b:
             s==3'b100 ? a << 1:
             s==3'b101 ? a >> 1:
             s==3'b110 ? a + b : a - b ;
endmodule

app/03/3kai/dpath.v
`include "def.h"
module dpath(
input clk, input rst_n, 
input [`DATA_W-1:0] datain,
input [`SEL_W-1:0] com,
output reg [`DATA_W-1:0] accum);

wire [`DATA_W-1:0] alu_y;

assign accout = accum;
alu alu_1(.a(accum), .b(datain), .s(com), .y(alu_y));

always @(posedge clk or negedge rst_n) 
begin
    if(!rst_n) accum <= `DATA_W'b0;
    else accum <= alu_y;
end
endmodule

app/03/3kai/test_dpath.v
/* test bench */
`timescale 1ns/1ps
`include "def.h"
module test;
parameter STEP = 10;
   reg clk, rst_n;
   reg [`SEL_W-1:0] s;
   reg [`DATA_W-1:0] b ;
   wire [`DATA_W-1:0] accum;
   dpath dpath0(.clk(clk), .rst_n(rst_n), .com(s),
               .datain(b), .accum(accum));
   initial begin
      $dumpfile("dpath.vcd");
      $dumpvars(0,test);
      clk <= 0;
      rst_n <= 0;
  #STEP rst_n <= 1;
	s<= 3'b001; b<=16'h2222;
  #STEP clk <=1; #STEP clk <=0;
     $display("s:%b b:%h accum:%h", s, b, accum);
	s<= 3'b110; b<=16'h3333;
  #STEP clk <=1; #STEP clk <=0;
     $display("s:%b b:%h accum:%h", s, b, accum);
	s<= 3'b111; b<=16'h1111;
  #STEP clk <=1; #STEP clk <=0;
     $display("s:%b b:%h accum:%h", s, b, accum);
	s<= 3'b110; b<=16'h4444;
  #STEP clk <=1; #STEP clk <=0;
     $display("s:%b b:%h accum:%h", s, b, accum);
	 $finish;
  end
endmodule

app/03/3kai/dpath.vcd
$date
	Tue Oct 11 02:29:57 2022
$end
$version
	Icarus Verilog
$end
$timescale
	1ps
$end
$scope module test $end
$var wire 16 ! accum [15:0] $end
$var reg 16 " b [15:0] $end
$var reg 1 # clk $end
$var reg 1 $ rst_n $end
$var reg 3 % s [2:0] $end
$scope module dpath0 $end
$var wire 1 # clk $end
$var wire 3 & com [2:0] $end
$var wire 16 ' datain [15:0] $end
$var wire 1 $ rst_n $end
$var wire 16 ( alu_y [15:0] $end
$var wire 1 ) accout $end
$var reg 16 * accum [15:0] $end
$scope module alu_1 $end
$var wire 16 + a [15:0] $end
$var wire 16 , b [15:0] $end
$var wire 3 - s [2:0] $end
$var wire 16 . y [15:0] $end
$upscope $end
$upscope $end
$upscope $end
$enddefinitions $end
#0
$dumpvars
bx .
bx -
bx ,
b0 +
b0 *
0)
bx (
bx '
bx &
bx %
0$
0#
bx "
b0 !
$end
#10000
b10001000100010 (
b10001000100010 .
b10001000100010 "
b10001000100010 '
b10001000100010 ,
b1 %
b1 &
b1 -
1$
#20000
b10001000100010 !
b10001000100010 *
b10001000100010 +
1#
#30000
b101010101010101 (
b101010101010101 .
b11001100110011 "
b11001100110011 '
b11001100110011 ,
b110 %
b110 &
b110 -
0#
#40000
b1000100010001000 (
b1000100010001000 .
1)
b101010101010101 !
b101010101010101 *
b101010101010101 +
1#
#50000
b100010001000100 (
b100010001000100 .
b1000100010001 "
b1000100010001 '
b1000100010001 ,
b111 %
b111 &
b111 -
0#
#60000
b11001100110011 (
b11001100110011 .
0)
b100010001000100 !
b100010001000100 *
b100010001000100 +
1#
#70000
b1000100010001000 (
b1000100010001000 .
b100010001000100 "
b100010001000100 '
b100010001000100 ,
b110 %
b110 &
b110 -
0#
#80000
b1100110011001100 (
b1100110011001100 .
b1000100010001000 !
b1000100010001000 *
b1000100010001000 +
1#
