app/05/pocoisa/rfile.v
`include "def.h"
module rfile (
 input clk,
 input [`REG_W-1:0] aadr, badr, cadr,
 output [`DATA_W-1:0] a, b,
 input [`DATA_W-1:0] c, 
 input we);

	reg [`DATA_W-1:0] r0, r1, r2, r3, r4, r5, r6, r7;

	assign a = aadr == 0 ? r0:
		aadr == 1 ? r1:
		aadr == 2 ? r2:
		aadr == 3 ? r3:
		aadr == 4 ? r4:
		aadr == 5 ? r5:
		aadr == 6 ? r6: r7;
	assign b = badr == 0 ? r0:
		badr == 1 ? r1:
		badr == 2 ? r2:
		badr == 3 ? r3:
		badr == 4 ? r4:
		badr == 5 ? r5:
		badr == 6 ? r6: r7;

	always @(posedge clk) begin
		if(we) 
		case(cadr) 
			0: r0 <= c;
			1: r1 <= c;
			2: r2 <= c;
			3: r3 <= c;
			4: r4 <= c;
			5: r5 <= c;
			6: r6 <= c;
			default: r7 <= c;
		endcase
	end

endmodule

app/02/alu0.v
module alu (
    input  [15:0] a,
    b,
    input  [ 2:0] s,
    output [15:0] y
);

  assign y = s==3'b000 ? a:
             s==3'b001 ? b:
             s==3'b010 ? a & b:
             s==3'b011 ? a | b:
             s==3'b100 ? a << 1:
             s==3'b101 ? a >> 1:
             s==3'b110 ? a + b : a - b ;
endmodule

app/06/branch/poco.v
`include "def.h"
module poco(
input clk, rst_n,
input [`DATA_W-1:0] idatain,
input [`DATA_W-1:0] ddatain,
output [`DATA_W-1:0] iaddr, daddr,
output [`DATA_W-1:0] ddataout,
output we);

reg [`DATA_W-1:0] pc;
wire [`DATA_W-1:0] rf_a, rf_b, rf_c;
wire [`DATA_W-1:0] alu_b, alu_y;
wire [`OPCODE_W-1:0] opcode;
wire [`OPCODE_W-1:0] func;
wire [`REG_W-1:0] rs, rd;
wire [`SEL_W-1:0] com;
wire [`IMM_W-1:0] imm;
wire rwe;
wire st_op, bez_op, bnz_op, addi_op, ld_op, alu_op;
wire ldi_op, ldiu_op, addiu_op;
wire bmi_op, bpl_op, jmp_op, jr_op;

assign ddataout = rf_a;
assign iaddr = pc;
assign daddr = rf_b;

assign {opcode, rd, rs, func} = idatain;
assign imm = idatain[`IMM_W-1:0];

// Decorder
assign st_op = (opcode == `OP_REG) & (func == `F_ST);
assign ld_op = (opcode == `OP_REG) & (func == `F_LD);
assign jr_op = (opcode == `OP_REG) & (func == `F_JR);
assign alu_op = (opcode == `OP_REG) & (func[4:3] == 2'b00); assign ldi_op = (opcode == `OP_LDI);
assign ldiu_op = (opcode == `OP_LDIU);
assign addi_op = (opcode == `OP_ADDI);
assign addiu_op = (opcode == `OP_ADDIU);
assign bez_op = (opcode == `OP_BEZ);
assign bnz_op = (opcode == `OP_BNZ);
assign bmi_op = (opcode == `OP_BMI);
assign bpl_op = (opcode == `OP_BPL);
assign jmp_op = (opcode == `OP_JMP);

assign we = st_op;

assign alu_b = (addi_op | ldi_op) ? {{8{imm[7]}},imm} :
		(addiu_op | ldiu_op) ? {8'b0,imm} : rf_b;

assign com = (addi_op | addiu_op ) ? `ALU_ADD: 
		(ldi_op | ldiu_op ) ? `ALU_THB: func[`SEL_W-1:0];

assign rf_c = ld_op  ? ddatain : alu_y;
assign rwe = ld_op  | alu_op | ldi_op | ldiu_op | addi_op | addiu_op  ;

alu alu_1(.a(rf_a), .b(alu_b), .s(com), .y(alu_y));

rfile rfile_1(.clk(clk), .a(rf_a), .aadr(rd), .b(rf_b), .badr(rs), 
	.c(rf_c), .cadr(rd), .we(rwe));

always @(posedge clk or negedge rst_n) 
begin 
   if(!rst_n) pc <= 0;
   else if ((bez_op & rf_a == 16'b0 ) | (bnz_op & rf_a != 16'b0) |
   			(bpl_op & ~rf_a[15]) | (bmi_op & rf_a[15]) )
     pc <= pc +{{8{imm[7]}},imm}+1 ;
   else if(jmp_op)
     pc <= pc +{{5{idatain[10]}},idatain[10:0]}+1 ;
   else if(jr_op)
   	 pc <= rf_a;
   else 
     pc <= pc+1;
end

endmodule

app/06/branch/test_poco.v
/* test bench */
`timescale 1ns/1ps
`include "def.h"
module test;
parameter STEP = 10;
   reg clk, rst_n;
   wire [`DATA_W-1:0] ddataout ;
   wire [`DATA_W-1:0] daddr, iaddr;
   wire we;
   reg [`DATA_W-1:0] dmem [0:`DEPTH-1];
   reg [`DATA_W-1:0] imem [0:`DEPTH-1];

   always #(STEP/2) begin
            clk <= ~clk;
   end

   poco poco_1(.clk(clk), .rst_n(rst_n), .idatain(imem[iaddr]),
               .ddatain(dmem[daddr]), .iaddr(iaddr), .daddr(daddr),
               .ddataout(ddataout), .we(we));

   always @(posedge clk) 
   begin 
      if(we) dmem[daddr] <= ddataout;
   end

   initial begin
      $dumpfile("poco.vcd");
      $dumpvars(0,test);
      $readmemh("dmem.dat", dmem);
      $readmemb("imem.dat", imem);
      clk <= `DISABLE;
      rst_n <= `ENABLE_N;
   #(STEP*1/4)
   #STEP
      rst_n <= `DISABLE_N;
   #(STEP*100)            
   $finish;
   end

   always @(negedge clk) begin
      $display("pc:%h idatain:%b ", poco_1.pc, poco_1.idatain);
      $display("reg:%h %h %h %h %h %h %h %h", 
	poco_1.rfile_1.r0, poco_1.rfile_1.r1, poco_1.rfile_1.r2,
	poco_1.rfile_1.r3, poco_1.rfile_1.r4, poco_1.rfile_1.r5,
	poco_1.rfile_1.r6, poco_1.rfile_1.r7);
      $display("dmem:%h %h %h %h dmem[8]%h", dmem[0], dmem[1], dmem[2], dmem[3], dmem[8]);
   end
endmodule

app/06/branch/poco.vcd
$date
	Sun Nov  6 05:06:53 2022
$end
$version
	Icarus Verilog
$end
$timescale
	1ps
$end
$scope module test $end
$var wire 1 ! we $end
$var wire 16 " iaddr [15:0] $end
$var wire 16 # ddataout [15:0] $end
$var wire 16 $ daddr [15:0] $end
$var reg 1 % clk $end
$var reg 1 & rst_n $end
$scope module poco_1 $end
$var wire 1 ' alu_op $end
$var wire 1 % clk $end
$var wire 16 ( daddr [15:0] $end
$var wire 16 ) ddatain [15:0] $end
$var wire 16 * ddataout [15:0] $end
$var wire 16 + idatain [15:0] $end
$var wire 1 , jr_op $end
$var wire 1 - ld_op $end
$var wire 1 & rst_n $end
$var wire 1 . rwe $end
$var wire 1 / st_op $end
$var wire 1 ! we $end
$var wire 3 0 rs [2:0] $end
$var wire 16 1 rf_c [15:0] $end
$var wire 16 2 rf_b [15:0] $end
$var wire 16 3 rf_a [15:0] $end
$var wire 3 4 rd [2:0] $end
$var wire 5 5 opcode [4:0] $end
$var wire 1 6 ldiu_op $end
$var wire 1 7 ldi_op $end
$var wire 1 8 jmp_op $end
$var wire 8 9 imm [7:0] $end
$var wire 16 : iaddr [15:0] $end
$var wire 5 ; func [4:0] $end
$var wire 3 < com [2:0] $end
$var wire 1 = bpl_op $end
$var wire 1 > bnz_op $end
$var wire 1 ? bmi_op $end
$var wire 1 @ bez_op $end
$var wire 16 A alu_y [15:0] $end
$var wire 16 B alu_b [15:0] $end
$var wire 1 C addiu_op $end
$var wire 1 D addi_op $end
$var reg 16 E pc [15:0] $end
$scope module alu_1 $end
$var wire 16 F b [15:0] $end
$var wire 3 G s [2:0] $end
$var wire 16 H y [15:0] $end
$var wire 16 I a [15:0] $end
$upscope $end
$scope module rfile_1 $end
$var wire 3 J aadr [2:0] $end
$var wire 3 K badr [2:0] $end
$var wire 16 L c [15:0] $end
$var wire 3 M cadr [2:0] $end
$var wire 1 % clk $end
$var wire 1 . we $end
$var wire 16 N b [15:0] $end
$var wire 16 O a [15:0] $end
$var reg 16 P r0 [15:0] $end
$var reg 16 Q r1 [15:0] $end
$var reg 16 R r2 [15:0] $end
$var reg 16 S r3 [15:0] $end
$var reg 16 T r4 [15:0] $end
$var reg 16 U r5 [15:0] $end
$var reg 16 V r6 [15:0] $end
$var reg 16 W r7 [15:0] $end
$upscope $end
$upscope $end
$upscope $end
$enddefinitions $end
#0
$dumpvars
bx W
bx V
bx U
bx T
bx S
bx R
bx Q
bx P
bx O
bx N
b0 M
b10 L
b0 K
b0 J
bx I
b10 H
b1 G
b10 F
b0 E
0D
0C
b10 B
b10 A
0@
0?
0>
0=
b1 <
b10 ;
b0 :
b10 9
08
07
16
b1001 5
b0 4
bx 3
bx 2
b10 1
b0 0
0/
1.
0-
0,
b100100000000010 +
bx *
bx )
bx (
0'
0&
0%
bx $
bx #
b0 "
0!
$end
#5000
b10 #
b10 *
b10 3
b10 I
b10 O
b101 )
b10 $
b10 (
b10 2
b10 N
b10 P
1%
#10000
0%
#12000
1&
#15000
b10 A
b10 H
1.
b101 1
b101 L
b10 B
b10 F
bx #
bx *
bx 3
bx I
bx O
1-
06
b0 5
b1 4
b1 J
b1 M
b1001 ;
b1001 9
b100001001 +
b1 "
b1 :
b1 E
1%
#20000
0%
#25000
b11 A
b11 H
b11 B
b11 F
b11 1
b11 L
b10 #
b10 *
b10 3
b10 I
b10 O
0-
16
b1001 5
b0 4
b0 J
b0 M
b11 ;
b11 9
b101 Q
b100100000000011 +
b10 "
b10 :
b10 E
1%
#30000
0%
#35000
b11 A
b11 H
1.
b11 B
b11 F
1-
bx #
bx *
bx 3
bx I
bx O
b11 )
b11 $
b11 (
b11 2
b11 N
06
b0 5
b10 4
b10 J
b10 M
b1001 ;
b1001 9
b11 P
b1000001001 +
b11 "
b11 :
b11 E
1%
#40000
0%
#45000
b0 1
b0 L
b0 A
b0 H
b0 B
b0 F
0-
16
b1001 5
b11 4
b11 J
b11 M
b0 ;
b0 9
b11 R
b100101100000000 +
b100 "
b100 :
b100 E
1%
#50000
0%
#55000
b101 1
b101 L
b101 A
b101 H
b0 #
b0 *
b0 3
b0 I
b0 O
1.
b110 <
b110 G
b101 B
b101 F
1'
b1001 )
b101 $
b101 (
b101 2
b101 N
06
b0 5
b1 0
b1 K
b110 ;
b100110 9
b0 S
b1100100110 +
b101 "
b101 :
b101 E
1%
#60000
0%
#65000
b10 1
b10 L
b10 A
b10 H
b11 #
b11 *
b11 3
b11 I
b11 O
b1111111111111111 B
b1111111111111111 F
bx )
bx $
bx (
bx 2
bx N
0'
1D
b1100 5
b10 4
b10 J
b10 M
b111 0
b111 K
b11111 ;
b11111111 9
b101 S
b110001011111111 +
b110 "
b110 :
b110 E
1%
#70000
0%
#75000
b1 1
b1 L
b1 A
b1 H
b10 #
b10 *
b10 3
b10 I
b10 O
0.
b101 <
b101 G
bx B
bx F
0D
1>
b10001 5
b11101 ;
b11111101 9
b10 R
b1000101011111101 +
b111 "
b111 :
b111 E
1%
#80000
0%
#85000
b1010 1
b1010 L
b1010 A
b1010 H
1.
b101 B
b101 F
b101 #
b101 *
b101 3
b101 I
b101 O
b110 <
b110 G
b1001 )
b101 $
b101 (
b101 2
b101 N
1'
0>
b0 5
b11 4
b11 J
b11 M
b1 0
b1 K
b110 ;
b100110 9
b1100100110 +
b101 "
b101 :
b101 E
1%
#90000
0%
#95000
b1 1
b1 L
b1 A
b1 H
b10 #
b10 *
b10 3
b10 I
b10 O
b1111111111111111 B
b1111111111111111 F
bx )
bx $
bx (
bx 2
bx N
0'
1D
b1100 5
b10 4
b10 J
b10 M
b111 0
b111 K
b11111 ;
b11111111 9
b1010 S
b110001011111111 +
b110 "
b110 :
b110 E
1%
#100000
0%
#105000
b0 1
b0 L
b0 A
b0 H
b1 #
b1 *
b1 3
b1 I
b1 O
0.
b101 <
b101 G
bx B
bx F
0D
1>
b10001 5
b11101 ;
b11111101 9
b1 R
b1000101011111101 +
b111 "
b111 :
b111 E
1%
#110000
0%
#115000
b1111 1
b1111 L
b1111 A
b1111 H
1.
b101 B
b101 F
b1010 #
b1010 *
b1010 3
b1010 I
b1010 O
b110 <
b110 G
b1001 )
b101 $
b101 (
b101 2
b101 N
1'
0>
b0 5
b11 4
b11 J
b11 M
b1 0
b1 K
b110 ;
b100110 9
b1100100110 +
b101 "
b101 :
b101 E
1%
#120000
0%
#125000
b0 1
b0 L
b0 A
b0 H
b1 #
b1 *
b1 3
b1 I
b1 O
b1111111111111111 B
b1111111111111111 F
bx )
bx $
bx (
bx 2
bx N
0'
1D
b1100 5
b10 4
b10 J
b10 M
b111 0
b111 K
b11111 ;
b11111111 9
b1111 S
b110001011111111 +
b110 "
b110 :
b110 E
1%
#130000
0%
#135000
b0 #
b0 *
b0 3
b0 I
b0 O
0.
b101 <
b101 G
bx B
bx F
0D
1>
b10001 5
b11101 ;
b11111101 9
b0 R
b1000101011111101 +
b111 "
b111 :
b111 E
1%
#140000
0%
#145000
1.
b0 B
b0 F
b1 <
b1 G
b11 #
b11 *
b11 3
b11 I
b11 O
b11 )
b11 $
b11 (
b11 2
b11 N
16
0>
b1001 5
b0 4
b0 J
b0 M
b0 0
b0 K
b0 ;
b0 9
b100100000000000 +
b1000 "
b1000 :
b1000 E
1%
#150000
0%
#155000
b1111 1
b1111 L
b1111 A
b1111 H
0.
b0 <
b0 G
b0 B
b0 F
1!
1/
b1111 #
b1111 *
b1111 3
b1111 I
b1111 O
b1 )
b0 $
b0 (
b0 2
b0 N
06
b0 5
b11 4
b11 J
b11 M
b1000 ;
b1000 9
b0 P
b1100001000 +
b1001 "
b1001 :
b1001 E
1%
#160000
0%
#165000
bx 1
bx L
bx A
bx H
b0 #
b0 *
b0 3
b0 I
b0 O
bx B
bx F
b111 <
b111 G
bx $
bx (
bx 2
bx N
0!
0/
1@
b10000 5
b10 4
b10 J
b10 M
b111 0
b111 K
b11111 ;
b11111111 9
bx )
b1000001011111111 +
b1010 "
b1010 :
b1010 E
1%
